cogwatch/__init__.py
cogwatch/cogwatch.py
cogwatch-3.3.0.dist-info/LICENSE
cogwatch-3.3.0.dist-info/METADATA
cogwatch-3.3.0.dist-info/WHEEL
cogwatch-3.3.0.dist-info/entry_points.txt
cogwatch-3.3.0.dist-info/RECORD
