Metadata-Version: 2.1
Name: cogwatch
Version: 3.3.0
Summary: Automatic hot-reloading for your discord.py (or other supported libaries) command files.
Home-page: https://github.com/robertwayne/cogwatch
License: MIT
Keywords: discord.py,discord bot,cogs,hot-reload,nextcord,py-cord,pycord,disnake,discord4py
Author: Rob Wagner
Author-email: rob@sombia.com
Requires-Python: >=3.10,<4.0
Classifier: Development Status :: 5 - Production/Stable
Classifier: Intended Audience :: Developers
Classifier: License :: OSI Approved :: MIT License
Classifier: Operating System :: OS Independent
Classifier: Programming Language :: Python :: 3
Classifier: Programming Language :: Python :: 3.10
Classifier: Programming Language :: Python :: 3.11
Classifier: Topic :: Communications :: Chat
Classifier: Typing :: Typed
Requires-Dist: watchfiles (>=0.15,<0.16)
Project-URL: Repository, https://github.com/robertwayne/cogwatch
